{
  "id": "bosnian_genocide_1992",
  "name": "Bosnian Genocide (including Srebrenica)",
  "status": "historic",
  "period": {
    "start": 1992,
    "end": 1995
  },
  "geography": {
    "region": "Southeastern Europe (Bosnia and Herzegovina)",
    "coordinates": [
      44.0,
      18.0
    ]
  },
  "participants": {
    "perpetrators": [
      "Republika Srpska",
      "VRS (Army of Republika Srpska)",
      "Serbian paramilitaries"
    ],
    "victims": [
      "Bosniak Muslims",
      "Bosnian Croats"
    ]
  },
  "metrics": {
    "mortality": {
      "min": 100000,
      "max": 110000,
      "population_initial": 1900000,
      "population_loss_percent": 5.0,
      "confidence": "high",
      "note": "Includes Srebrenica massacre (8,000+ men and boys in July 1995). 2.2 million displaced. Well-documented due to ICTY prosecutions."
    },
    "scores": {
      "systematic_intensity": 88,
      "profit": 0,
      "ideology": 80,
      "complicity": 60
    },
    "breakdowns": {
      "systematic_intensity": {
        "policy": true,
        "state_involvement": true,
        "infrastructure": true,
        "propaganda": true,
        "generational_targeting": true,
        "cultural_ban": true,
        "property_seizure": true,
        "identification": true,
        "deliberate_deprivation": false
      },
      "profit": {
        "direct_revenue": false,
        "resource_extraction": false,
        "forced_labor": false,
        "economic_dependence": false,
        "market_integration": false
      },
      "ideology": {
        "purity_ideal": true,
        "dehumanization": true,
        "mass_mobilization": false,
        "existential_threat": true,
        "utopianism": true
      },
      "complicity": {
        "distance": false,
        "benefit": true,
        "euphemisms": true,
        "diffused_responsibility": true,
        "silence": false
      }
    },
    "rationales": {
      "systematic_intensity": "Ethnic cleansing, concentration camps, Srebrenica massacre. Systematic targeting.",
      "profit": "Land and property seizure for ethnic homogeneity.",
      "ideology": "Serbian nationalism, Greater Serbia project. Ethnic purification.",
      "complicity": "Serbian military, paramilitaries, some civilians. UN failed to protect. ICTY prosecutions."
    }
  },
  "tags": [
    "ethnic_cleansing",
    "ideology_driven",
    "concentration_camps",
    "post_cold_war"
  ],
  "denial_status": "acknowledged",
  "analysis": {
    "tier": "INDUSTRIAL MEGA-EVENT",
    "pattern_note": "First genocide in Europe since WWII. Coined term 'ethnic cleansing'. UN peacekeepers present at Srebrenica but failed to prevent massacre. ICTY prosecutions established legal precedents. Demonstrates genocide can happen in modern Europe with international observers watching.",
    "warning_signs": [
      "Nationalist rhetoric of ethnic purity",
      "Historical grievances weaponized",
      "Ethnic cleansing for 'Greater Serbia'"
    ],
    "root_causes": "Yugoslav collapse, Serbian nationalism, historical tensions, weak international response",
    "pattern_tags": [
      "DEHUMANIZATION",
      "ECONOMIC_CRISIS",
      "ETHNIC_NATIONALISM",
      "FORCED_DISPLACEMENT",
      "INTERNATIONAL_INACTION",
      "MEDIA_INCITEMENT",
      "PROPERTY_SEIZURE"
    ]
  },
  "erasure_note": "National Library of Sarajevo deliberately targeted with incendiary shells (August 25-26, 1992). 1.5 million volumes and 155,000 rare books destroyed. Firefighters shot at by snipers. Unique records of Bosnian coexistence lost.",
  "sources": [
    {
      "title": "Srebrenica: Record of a War Crime",
      "author": "Jan Willem Honig",
      "year": 1996
    },
    {
      "title": "The War in Bosnia-Herzegovina: Ethnic Conflict and International Intervention",
      "author": "Steven Burg",
      "year": 1999
    }
  ],
  "wikipedia_url": "https://en.wikipedia.org/wiki/Bosnian_genocide"
}
