{
  "id": "rwandan_genocide_1994",
  "name": "Rwandan Genocide",
  "status": "historic",
  "period": {
    "start": 1994,
    "end": 1994
  },
  "geography": {
    "region": "Central Africa (Rwanda)",
    "coordinates": [
      -2.0,
      30.0
    ]
  },
  "participants": {
    "perpetrators": [
      "Hutu extremists",
      "Interahamwe militia",
      "Rwandan government"
    ],
    "victims": [
      "Tutsi",
      "Moderate Hutu"
    ]
  },
  "metrics": {
    "mortality": {
      "min": 500000,
      "max": 1000000,
      "population_initial": 1000000,
      "population_loss_percent": 70.0,
      "confidence": "medium",
      "note": "Approximately 70% of Rwanda's Tutsi population killed in ~100 days."
    },
    "scores": {
      "systematic_intensity": 67,
      "profit": 0,
      "ideology": 100,
      "complicity": 80
    },
    "breakdowns": {
      "systematic_intensity": {
        "policy": true,
        "state_involvement": true,
        "infrastructure": false,
        "propaganda": true,
        "broad_targeting": true,
        "cultural_ban": false,
        "property_seizure": true,
        "identification": true,
        "biological_warfare": false
      },
      "profit": {
        "direct_revenue": false,
        "resource_extraction": false,
        "forced_labor": false,
        "economic_dependence": false,
        "market_integration": false
      },
      "ideology": {
        "purity_ideal": true,
        "historical_claim": true,
        "higher_purpose": true,
        "victim_narrative": true,
        "utopianism": true
      },
      "complicity": {
        "distance": false,
        "benefit": true,
        "euphemisms": true,
        "diffused_responsibility": true,
        "silence": true
      }
    }
  },
  "tags": [
    "ideology_driven",
    "rapid_genocide",
    "radio_propaganda",
    "neighbor_violence"
  ],
  "denial_status": "acknowledged",
  "analysis": {
    "tier": "INDUSTRIAL MEGA-EVENT",
    "pattern_note": "Challenges the '>5 years' criterion - extreme intensity achieved in only 100 days. RTLM radio coordinated killings. ID cards marked ethnicity enabling systematic targeting. Demonstrates ideology can mobilize faster than bureaucracy."
  },
  "sources": [
    {
      "title": "We Wish to Inform You That Tomorrow We Will Be Killed with Our Families",
      "author": "Philip Gourevitch",
      "year": 1998
    },
    {
      "title": "Leave None to Tell the Story",
      "author": "Human Rights Watch",
      "year": 1999
    }
  ]
}